czmlpy/__init__.py
czmlpy/base.py
czmlpy/common.py
czmlpy/constants.py
czmlpy/core.py
czmlpy/enums.py
czmlpy/properties.py
czmlpy/py.typed
czmlpy/types.py
czmlpy/utils.py
czmlpy/widget.py
czmlpy/examples/__init__.py
czmlpy/examples/simple.py
czmlpy-0.9.0.dist-info/LICENSE
czmlpy-0.9.0.dist-info/METADATA
czmlpy-0.9.0.dist-info/WHEEL
czmlpy-0.9.0.dist-info/top_level.txt
czmlpy-0.9.0.dist-info/RECORD
