Metadata-Version: 2.1
Name: czmlpy
Version: 0.9.0
Summary: Python 3 library to write CZML
Home-page: https://github.com/mixxen/czmlpy
Download-URL: https://github.com/mixxen/czmlpy
Author: Juan Luis Cano Rodríguez
Author-email: hello@juanlu.space
License: MIT
Project-URL: Source, https://github.com/mixxen/czmlpy
Project-URL: Tracker, https://github.com/mixxen/czmlpy/issues
Keywords: czml,cesium,orbits
Platform: any
Classifier: Development Status :: 3 - Alpha
Classifier: Intended Audience :: Education
Classifier: Intended Audience :: Science/Research
Classifier: License :: OSI Approved :: MIT License
Classifier: Operating System :: OS Independent
Classifier: Programming Language :: Python
Classifier: Programming Language :: Python :: 3
Classifier: Programming Language :: Python :: 3.5
Classifier: Programming Language :: Python :: 3.6
Classifier: Programming Language :: Python :: 3.7
Classifier: Programming Language :: Python :: 3.8
Classifier: Programming Language :: Python :: Implementation :: CPython
Classifier: Topic :: Scientific/Engineering
Classifier: Topic :: Scientific/Engineering :: Physics
Classifier: Topic :: Scientific/Engineering :: Astronomy
Requires-Python: >=3.7
License-File: LICENSE
Requires-Dist: attrs (>=19.2)
Requires-Dist: python-dateutil (<3,>=2.7)
Requires-Dist: w3lib
Provides-Extra: dev
Requires-Dist: astropy ; extra == 'dev'
Requires-Dist: pytest ; extra == 'dev'
Requires-Dist: pytest-cov ; extra == 'dev'
Requires-Dist: pytest-mypy ; extra == 'dev'
Requires-Dist: types-python-dateutil ; extra == 'dev'
